imsholcal/__init__.py
imsholcal/business_day.py
imsholcal-1.1.4.dist-info/METADATA
imsholcal-1.1.4.dist-info/WHEEL
imsholcal-1.1.4.dist-info/top_level.txt
imsholcal-1.1.4.dist-info/RECORD
