Metadata-Version: 2.1
Name: imsholcal
Version: 1.1.4
Summary: business day offset function with custom exchange based holiday calendar
Home-page: https://github.com/mcunningto/imsholcal
Author: mcunningto
Author-email: mcunningto@gmail.com
License: MIT
Requires-Dist: pandas
Requires-Dist: requests
Requires-Dist: requests-cache
